{"errors":[{"message":"Cannot destructure property `src` of 'undefined' or 'null'.","locations":[{"line":42,"column":3}],"path":["posts","edges",0,"node","frontmatter","cover","children",0,"fluid","srcWebp"]},{"message":"Cannot destructure property `srcSet` of 'undefined' or 'null'.","locations":[{"line":43,"column":3}],"path":["posts","edges",0,"node","frontmatter","cover","children",0,"fluid","srcSetWebp"]}],"data":{"posts":{"edges":[{"node":{"excerpt":"At least once in life, every computer user has to handle some spreadsheets or, excel files. Sometimes to put formulas in for accounting…","fields":{"slug":"/dummy-post-1/","prefix":"2017-10-01"},"frontmatter":{"title":"Cooking big Excel files with Python and Openpyxl","category":"python","author":"Shawon Ashraf","cover":{"children":[{"__typename":"ImageSharp","fluid":{"base64":null,"aspectRatio":null,"src":null,"srcSet":null,"srcWebp":null,"srcSetWebp":null,"sizes":null}}]}}}},{"node":{"excerpt":"At least once in life, every computer user has to handle some spreadsheets or, excel files. Sometimes to put formulas in for accounting…","fields":{"slug":"/cook-big-excel-py/","prefix":"2017-10-01"},"frontmatter":{"title":"Cooking big Excel files with Python and Openpyxl","category":"python","author":"Shawon Ashraf","cover":null}}}]},"site":{"siteMetadata":{"facebook":{"appId":""}}}},"pageContext":{}}